technical_analysis/__init__.py
technical_analysis/__main__.py
technical_analysis/backtest_data.py
technical_analysis/broker_stock_analysis.py
technical_analysis/etf_screener.py
technical_analysis/fc.py
technical_analysis/grid_loader.py
technical_analysis/grid_strategy_backtest.py
technical_analysis/http_server.py
technical_analysis/main.py
technical_analysis/market_sentiment.py
technical_analysis/stock_data.py
technical_analysis/trading_strategy.py
technical_analysis/vector_db.py
technical_analysis_mcp-0.7.4.dist-info/METADATA
technical_analysis_mcp-0.7.4.dist-info/WHEEL
technical_analysis_mcp-0.7.4.dist-info/entry_points.txt
technical_analysis_mcp-0.7.4.dist-info/top_level.txt
technical_analysis_mcp-0.7.4.dist-info/RECORD
