Metadata-Version: 2.4
Name: technical-analysis-mcp
Version: 0.7.4
Summary: A Python package for technical analysis of financial markets
Author-email: libin <binlish81@qq.com>
License: MIT
Classifier: Development Status :: 3 - Alpha
Classifier: Intended Audience :: Financial and Insurance Industry
Classifier: License :: OSI Approved :: MIT License
Classifier: Programming Language :: Python :: 3.10
Requires-Python: >=3.9
Requires-Dist: akshare
Requires-Dist: pandas
Requires-Dist: openai
Requires-Dist: backtrader
Requires-Dist: mcp>=1.13.0
Requires-Dist: fastapi
Requires-Dist: scipy
